    {
        "events": [
            {
                "name": "Бригадный подряд",
                "date": "17.10",
                "desc": "Все старые хиты",
                "img": "img/test-images/1.jpg",
                "link": ""
            },
            {
                "name": "Бригадный подряд 2",
                "date": "17.01",
                "desc": "Все старые хиты",
                "img": "img/test-images/3.png",
                "link": ""
            },
            {
                "name": "Бригадный подряд 3",
                "date": "12.10",
                "desc": "Все старые хиты",
                "img": "img/test-images/4.png",
                "link": ""
            },
            {
                "name": "Бригадный подряд 4",
                "date": "19.10",
                "desc": "Все старые хиты",
                "img": "img/test-images/5.png",
                "link": ""
            },
            {
                "name": "Бригадный подряд 5",
                "date": "14.10",
                "desc": "Все старые хиты",
                "img": "img/test-images/6.png",
                "link": ""
            },
            {
                "name": "Бригадный подряд 6",
                "date": "15.10",
                "desc": "Все старые хиты",
                "img": "img/test-images/7.png",
                "link": ""
            },
            {
                "name": "Бригадный подряд 7",
                "date": "15.10",
                "desc": "Все старые хиты",
                "img": "img/test-images/8.png",
                "link": ""
            },
            {
                "name": "Бригадный подряд 8",
                "date": "15.10",
                "desc": "Все старые хиты",
                "img": "img/test-images/9.png",
                "link": ""
            },
            {
                "name": "Бригадный подряд 9",
                "date": "15.10",
                "desc": "Все старые хиты",
                "img": "img/test-images/4.png",
                "link": ""
            },
            {
                "name": "тролль гнет ель",
                "date": "11.10",
                "desc": "Все старые хиты",
                "img": "img/test-images/3.png",
                "link": ""
            },
            {
                "name": "тролль гнет ель 2",
                "date": "11.15",
                "desc": "Все Все старые хиты",
                "img": "img/test-images/2.png",
                "link": ""
            },
                        {
                            "name": "Бригадный подряд 3",
                            "date": "12.10",
                            "desc": "Все старые хиты",
                            "img": "img/test-images/1.jpg",
                            "link": ""
                        },
                        {
                            "name": "Бригадный подряд 4",
                            "date": "19.10",
                            "desc": "Все старые хиты",
                            "img": "img/test-images/7.png",
                            "link": ""
                        },
                        {
                            "name": "Бригадный подряд 5",
                            "date": "14.10",
                            "desc": "Все старые хиты",
                            "img": "img/test-images/9.png",
                            "link": ""
                        },
                        {
                            "name": "Бригадный подряд 6",
                            "date": "15.10",
                            "desc": "Все старые хиты",
                            "img": "img/test-images/6.png",
                            "link": ""
                        },
                        {
                            "name": "Бригадный подряд 7",
                            "date": "15.10",
                            "desc": "Все старые хиты",
                            "img": "img/test-images/1.jpg",
                            "link": ""
                        },
                        {
                            "name": "Бригадный подряд 8",
                            "date": "15.10",
                            "desc": "Все старые хиты",
                            "img": "img/test-images/5.png",
                            "link": ""
                        },
                        {
                            "name": "Бригадный подряд 9",
                            "date": "15.10",
                            "desc": "Все старые хиты",
                            "img": "img/test-images/3.png",
                            "link": ""
                        },
                        {
                            "name": "тролль гнет ель",
                            "date": "11.10",
                            "desc": "Все старые хиты",
                            "img": "img/test-images/4.png",
                            "link": ""
                        },
                        {
                            "name": "тролль гнет ель 2",
                            "date": "11.15",
                            "desc": "Все Все старые хиты",
                            "img": "img/test-images/6.png",
                            "link": ""
                        },
                                    {
                                        "name": "Бригадный подряд 6",
                                        "date": "15.10",
                                        "desc": "Все старые хиты",
                                        "img": "img/test-images/7.png",
                                        "link": ""
                                    },
                                    {
                                        "name": "Бригадный подряд 7",
                                        "date": "15.10",
                                        "desc": "Все старые хиты",
                                        "img": "img/test-images/8.png",
                                        "link": ""
                                    },
                                    {
                                        "name": "Бригадный подряд 8",
                                        "date": "15.10",
                                        "desc": "Все старые хиты",
                                        "img": "img/test-images/9.png",
                                        "link": ""
                                    },
                                    {
                                        "name": "Бригадный подряд 9",
                                        "date": "15.10",
                                        "desc": "Все старые хиты",
                                        "img": "img/test-images/4.png",
                                        "link": ""
                                    },
                                    {
                                        "name": "тролль гнет ель",
                                        "date": "11.10",
                                        "desc": "Все старые хиты",
                                        "img": "img/test-images/3.png",
                                        "link": ""
                                    },
                                    {
                                        "name": "тролль гнет ель 2",
                                        "date": "11.15",
                                        "desc": "Все Все старые хиты",
                                        "img": "img/test-images/2.png",
                                        "link": ""
                                    },
                                                {
                                                    "name": "Бригадный подряд 3",
                                                    "date": "12.10",
                                                    "desc": "Все старые хиты",
                                                    "img": "img/test-images/1.jpg",
                                                    "link": ""
                                                },
                                                                                   {
                                                                                        "name": "тролль гнет ель",
                                                                                        "date": "11.10",
                                                                                        "desc": "Все старые хиты",
                                                                                        "img": "img/test-images/3.png",
                                                                                        "link": ""
                                                                                    },
                                                                                    {
                                                                                        "name": "тролль гнет ель 2",
                                                                                        "date": "11.15",
                                                                                        "desc": "Все Все старые хиты",
                                                                                        "img": "img/test-images/2.png",
                                                                                        "link": ""
                                                                                    },
                                                                                                {
                                                                                                    "name": "Бригадный подряд 3",
                                                                                                    "date": "12.10",
                                                                                                    "desc": "Все старые хиты",
                                                                                                    "img": "img/test-images/1.jpg",
                                                                                                    "link": ""
                                                                                                }

        ]

    }
